AUTHORS
CONTRIBUTING.rst
ChangeLog
HACKING.rst
LICENSE
MANIFEST.in
README.md
README.rst
babel.cfg
requirements.txt
setup.cfg
setup.py
test-requirements.txt
tox.ini
doc/source/conf.py
doc/source/contributing.rst
doc/source/index.rst
doc/source/installation.rst
doc/source/readme.rst
doc/source/usage.rst
docker/centos/Dockerfile
horizon_bsn/__init__.py
horizon_bsn.egg-info/PKG-INFO
horizon_bsn.egg-info/SOURCES.txt
horizon_bsn.egg-info/dependency_links.txt
horizon_bsn.egg-info/not-zip-safe
horizon_bsn.egg-info/pbr.json
horizon_bsn.egg-info/top_level.txt
horizon_bsn/api/__init__.py
horizon_bsn/api/neutron.py
horizon_bsn/content/__init__.py
horizon_bsn/content/connections/README
horizon_bsn/content/connections/__init__.py
horizon_bsn/content/connections/panel.py
horizon_bsn/content/connections/tabs.py
horizon_bsn/content/connections/urls.py
horizon_bsn/content/connections/views.py
horizon_bsn/content/connections/network_template/__init__.py
horizon_bsn/content/connections/network_template/admin_forms.py
horizon_bsn/content/connections/network_template/admin_urls.py
horizon_bsn/content/connections/network_template/forms.py
horizon_bsn/content/connections/network_template/tables.py
horizon_bsn/content/connections/network_template/urls.py
horizon_bsn/content/connections/network_template/views.py
horizon_bsn/content/connections/reachability_tests/__init__.py
horizon_bsn/content/connections/reachability_tests/forms.py
horizon_bsn/content/connections/reachability_tests/rest_lib.py
horizon_bsn/content/connections/reachability_tests/tables.py
horizon_bsn/content/connections/reachability_tests/tabs.py
horizon_bsn/content/connections/reachability_tests/urls.py
horizon_bsn/content/connections/reachability_tests/views.py
horizon_bsn/content/connections/routerrules/__init__.py
horizon_bsn/content/connections/routerrules/forms.py
horizon_bsn/content/connections/routerrules/rulemanager.py
horizon_bsn/content/connections/routerrules/tables.py
horizon_bsn/content/connections/routerrules/tabs.py
horizon_bsn/content/connections/routerrules/urls.py
horizon_bsn/content/connections/routerrules/views.py
horizon_bsn/content/connections/sample_heat_templates/basic_3tier.yaml
