Metadata-Version: 1.1
Name: horizon-bsn
Version: 2015.2.7
Summary: Big Switch Networks Extension for the Openstack Dashboard (Horizon).
Home-page: http://www.bigswitch.com/
Author: Big Switch Networks
Author-email: horizon-bsn@bigswitch.com
License: UNKNOWN
Platform: UNKNOWN
Classifier: Environment :: OpenStack
Classifier: Intended Audience :: Information Technology
Classifier: Intended Audience :: System Administrators
Classifier: License :: OSI Approved :: Apache Software License
Classifier: Operating System :: POSIX :: Linux
Classifier: Programming Language :: Python
Classifier: Programming Language :: Python :: 2
Classifier: Programming Language :: Python :: 2.7
Classifier: Programming Language :: Python :: 3
Classifier: Programming Language :: Python :: 3.3
Classifier: Programming Language :: Python :: 3.4
